tinyblend.py
tinyblend-1.0.2.dist-info/METADATA
tinyblend-1.0.2.dist-info/WHEEL
tinyblend-1.0.2.dist-info/top_level.txt
tinyblend-1.0.2.dist-info/RECORD
